Metadata-Version: 2.1
Name: odoo-addon-energy_communities_cooperator
Version: 16.0.0.5.3
Requires-Python: >=3.10
Requires-Dist: odoo-addon-account_multicompany_easy_creation>=16.0dev,<16.1dev
Requires-Dist: odoo-addon-contract_variable_quantity>=16.0dev,<16.1dev
Requires-Dist: odoo-addon-cooperator>=16.0dev,<16.1dev
Requires-Dist: odoo-addon-cooperator_account_banking_mandate>=16.0dev,<16.1dev
Requires-Dist: odoo-addon-cooperator_account_payment>=16.0dev,<16.1dev
Requires-Dist: odoo-addon-energy_communities>=16.0dev,<16.1dev
Requires-Dist: odoo-addon-energy_communities_crm>=16.0dev,<16.1dev
Requires-Dist: odoo-addon-l10n_es_cooperator>=16.0dev,<16.1dev
Requires-Dist: odoo>=16.0a,<16.1dev
Summary: Energy communities cooperative membership management
Home-page: https://git.coopdevs.org/coopdevs/comunitats-energetiques/odoo-ce
License: AGPL-3
Author: Som Comunitats SCCL
Classifier: Programming Language :: Python
Classifier: Framework :: Odoo
Classifier: Framework :: Odoo :: 16.0
Classifier: License :: OSI Approved :: GNU Affero General Public License v3
